caneta/__init__.py
caneta/caneta.py
caneta/lapis.py
caneta-0.16.1.dist-info/WHEEL
caneta-0.16.1.dist-info/METADATA
caneta-0.16.1.dist-info/RECORD
